README.md
setup.py
helloworld/__init__.py
helloworld/_version.py
helloworld/greetings.py
pypi_holoniq_simple.egg-info/PKG-INFO
pypi_holoniq_simple.egg-info/SOURCES.txt
pypi_holoniq_simple.egg-info/dependency_links.txt
pypi_holoniq_simple.egg-info/requires.txt
pypi_holoniq_simple.egg-info/top_level.txt
tests/__init__.py
tests/test_helloworld.py