Metadata-Version: 2.1
Name: pypi-holoniq-simple
Version: 0.0.5
Summary: Say hello!
Home-page: https://github.com/stevej2608/pypi-holoniq-simple
Author: Steve Jones
Author-email: jonesst2608@gmail.com
License: MIT
Platform: UNKNOWN
Classifier: Programming Language :: Python :: 3
Classifier: Programming Language :: Python :: 3.6
Classifier: Programming Language :: Python :: 3.7
Classifier: License :: OSI Approved :: MIT License
Classifier: Operating System :: OS Independent
Provides-Extra: dev
